jupyterlab_frontegg/__init__.py
jupyterlab_frontegg/_version.py
jupyterlab_frontegg/labextension/build_log.json
jupyterlab_frontegg/labextension/package.json
jupyterlab_frontegg/labextension/static/lib_index_js.b1ab1cab32624e785fb4.js
jupyterlab_frontegg/labextension/static/lib_index_js.b1ab1cab32624e785fb4.js.map
jupyterlab_frontegg/labextension/static/remoteEntry.c738f55eec1ae0752e28.js
jupyterlab_frontegg/labextension/static/remoteEntry.c738f55eec1ae0752e28.js.map
jupyterlab_frontegg/labextension/static/style.js
jupyterlab_frontegg/labextension/static/style_index_js.2d049dfbb546572d6969.js
jupyterlab_frontegg/labextension/static/style_index_js.2d049dfbb546572d6969.js.map
jupyterlab_frontegg/labextension/static/vendors-node_modules_axios_index_js.ad04ded3d7ab54758b95.js
jupyterlab_frontegg/labextension/static/vendors-node_modules_axios_index_js.ad04ded3d7ab54758b95.js.map
jupyterlab_frontegg/labextension/static/vendors-node_modules_babel_runtime_helpers_esm_extends_js-node_modules_babel_runtime_helpers_-91be28.845b0891004e58fc6751.js
jupyterlab_frontegg/labextension/static/vendors-node_modules_babel_runtime_helpers_esm_extends_js-node_modules_babel_runtime_helpers_-91be28.845b0891004e58fc6751.js.map
jupyterlab_frontegg/labextension/static/vendors-node_modules_css-loader_dist_runtime_api_js-node_modules_css-loader_dist_runtime_cssW-926fd9.c3ce11bbc3fe744c482e.js
jupyterlab_frontegg/labextension/static/vendors-node_modules_css-loader_dist_runtime_api_js-node_modules_css-loader_dist_runtime_cssW-926fd9.c3ce11bbc3fe744c482e.js.map
jupyterlab_frontegg/labextension/static/vendors-node_modules_material-ui_core_esm_Paper_Paper_js-node_modules_material-ui_core_esm_st-36ed10.ed315751e3fd6eb0f613.js
jupyterlab_frontegg/labextension/static/vendors-node_modules_material-ui_core_esm_Paper_Paper_js-node_modules_material-ui_core_esm_st-36ed10.ed315751e3fd6eb0f613.js.map
jupyterlab_frontegg-0.1.0.dist-info/LICENSE
jupyterlab_frontegg-0.1.0.dist-info/METADATA
jupyterlab_frontegg-0.1.0.dist-info/WHEEL
jupyterlab_frontegg-0.1.0.dist-info/top_level.txt
jupyterlab_frontegg-0.1.0.dist-info/RECORD
